<?xml version="1.0" encoding="UTF-8" standalone="no"?>
<experiment version="1.4.0">
	<experimentViews>
		<tab name="Tab_1">
				</tab>
	</experimentViews>

	<watch width="945" height="738" visible="true" pos="right" >
		<currentTab name="view"/>
		<variables>
			<tab name="initial"> 
			</tab> 
			<tab name="inputs"> 
			</tab> 
			<tab name="view"> 
				<var name="of1.Q"/>
				<var name="of2.Q"/>
				<var name="of3.Q"/>
				<var name="p1.Q"/>
				<var name="p2.Q"/>
				<var name="p3.Q"/>
				<var name="p4.Q"/>
				<var name="p5.Q"/>
				<var name="p6.Q"/>
				<var name="t1.Q"/>
			</tab> 
		</variables>
		<layout>
			<tab name="initial"> 
				<column name="name" width="100"/> 
				<column name="value" width="100"/> 
				<column name="units" width="100"/> 
				<column name="category" width="100"/> 
				<column name="type" width="100"/> 
			</tab> 
			<tab name="inputs"> 
				<column name="name" width="100"/> 
				<column name="value" width="100"/> 
				<column name="units" width="100"/> 
				<column name="category" width="100"/> 
			</tab> 
			<tab name="view"> 
				<column name="name" width="100"/> 
				<column name="value" width="100"/> 
				<column name="units" width="100"/> 
				<column name="category" width="100"/> 
			</tab> 
		</layout>
	</watch>





	<outputWindow height="200" width="1920" visible="true" pos="bottom" />

	<alarms globalEnabled="TRUE">
	</alarms>


	<mainWindow  mode="maximized" currentTab="Tab_1" />
</experiment>